gblur-0.1.1.dist-info/METADATA
gblur-0.1.1.dist-info/WHEEL
gblur/__init__.py
gblur/gblur.cpython-36m-x86_64-linux-gnu.so
gblur-0.1.1.dist-info/RECORD
