Metadata-Version: 2.1
Name: gblur
Version: 0.1.1
Summary: Simple blur library for python written in Rust
Author: Megumin
